[{"id":"9028404tc","user_id":"12357906u","time":2399542,"value":" whyee","language":"en","stats":{"flags":{"inappropriate":0,"advertisement":0,"spoiler":0},"likes":0,"dislikes":0},"score":3.53,"user":{"id":"12357906u","name":"","username":"sakarambetanjo_198","staff":false,"images":{"avatar":{"url":"https://lh3.googleusercontent.com/-XdUIqdMkCWA/AAAAAAAAAAI/AAAAAAAAAAA/4252rscbv5M/photo.jpg?sz=215"}}}},{"id":"8991035tc","user_id":"9872615u","time":2749038,"value":"That was very bad","language":"en","stats":{"flags":{"inappropriate":0,"advertisement":0,"spoiler":0},"likes":0,"dislikes":0},"score":10.0,"user":{"id":"9872615u","name":"nalley","username":"atoabdi61_213","images":{"avatar":{"url":"https://lh3.googleusercontent.com/-XdUIqdMkCWA/AAAAAAAAAAI/AAAAAAAAAAA/4252rscbv5M/photo.jpg?sz=215"}},"staff":false}}]